idom_plotly/__init__.py
idom_plotly/bundle.js
idom_plotly/component.py
idom_plotly/py.typed
idom_plotly-0.0.3.dist-info/LICENSE
idom_plotly-0.0.3.dist-info/METADATA
idom_plotly-0.0.3.dist-info/WHEEL
idom_plotly-0.0.3.dist-info/top_level.txt
idom_plotly-0.0.3.dist-info/RECORD
