Metadata-Version: 2.1
Name: idom-plotly
Version: 0.0.3
Summary: Plotly figures as a custom component for IDOM
Home-page: https://github.com/idom-team/idom-plotly
Author: Ryan Morshead
Author-email: ryan.morshead@gmail.com
License: UNKNOWN
Keywords: idom,components
Platform: Linux
Platform: Mac OS X
Platform: Windows
Classifier: Environment :: Web Environment
Classifier: Intended Audience :: Developers
Classifier: Intended Audience :: Science/Research
Classifier: Programming Language :: Python :: 3.7
Classifier: Programming Language :: Python :: 3.8
Classifier: Programming Language :: Python :: 3.9
Classifier: Topic :: Software Development :: User Interfaces
Classifier: Topic :: Software Development :: Widget Sets
Classifier: Typing :: Typed
Requires-Python: >=3.8
License-File: LICENSE
Requires-Dist: idom (>=0.33.1)
Requires-Dist: plotly
